dlpx/__init__.py
dlpx/virtualization/__init__.py
dlpx/virtualization/platform/__init__.py
dlpx/virtualization/platform/_discovery.py
dlpx/virtualization/platform/_linked.py
dlpx/virtualization/platform/_plugin.py
dlpx/virtualization/platform/_plugin_classes.py
dlpx/virtualization/platform/_upgrade.py
dlpx/virtualization/platform/_virtual.py
dlpx/virtualization/platform/exceptions.py
dlpx/virtualization/platform/import_util.py
dlpx/virtualization/platform/import_validations.py
dlpx/virtualization/platform/migration_helper.py
dlpx/virtualization/platform/operation.py
dlpx/virtualization/platform/util.py
dlpx/virtualization/platform/validation_util.py
dvp_platform-5.0.1.dist-info/LICENSE
dvp_platform-5.0.1.dist-info/METADATA
dvp_platform-5.0.1.dist-info/WHEEL
dvp_platform-5.0.1.dist-info/top_level.txt
dvp_platform-5.0.1.dist-info/RECORD
